dataferry/__init__.py
dataferry/connections.py
dataferry/dimensions.py
dataferry/execution.py
dataferry/functions.py
dataferry/transfers.py
dataferry-0.0.6.dist-info/LICENSE
dataferry-0.0.6.dist-info/METADATA
dataferry-0.0.6.dist-info/WHEEL
dataferry-0.0.6.dist-info/top_level.txt
dataferry-0.0.6.dist-info/RECORD
