Metadata-Version: 2.1
Name: dataferry
Version: 0.0.6
Summary: Simple ETL tools and functions for SQL Server
Home-page: https://github.com/porteverte/dataferry
Author: Porte Verte
Author-email: Port Verte <porte_verte@outlook.com>
Project-URL: Homepage, https://github.com/porteverte/dataferry
Project-URL: Issues, https://github.com/porteverte/dataferry/issues
Classifier: Programming Language :: Python :: 3
Classifier: License :: OSI Approved :: MIT License
Classifier: Operating System :: OS Independent
Requires-Python: >=3.8
License-File: LICENSE
